matbii/__init__.py
matbii/__main__.py
matbii/main.py
matbii/agent/__init__.py
matbii/avatar/__init__.py
matbii/avatar/exit_actuator.py
matbii/config/__init__.py
matbii/environment/__init__.py
matbii/example/README.md
matbii/example/example-A/experiment.json
matbii/example/example-A/resource_management.json
matbii/example/example-A/resource_management.sch
matbii/example/example-A/system_monitoring.json
matbii/example/example-A/system_monitoring.sch
matbii/example/example-A/tracking.json
matbii/example/example-A/tracking.sch
matbii/example/example-B/experiment.json
matbii/example/example-B/resource_management.json
matbii/example/example-B/resource_management.sch
matbii/example/example-B/system_monitoring.json
matbii/example/example-B/system_monitoring.sch
matbii/example/example-B/tracking.json
matbii/example/example-B/tracking.sch
matbii/example/only-system-monitoring/experiment.json
matbii/example/only-system-monitoring/system_monitoring.json
matbii/example/only-system-monitoring/system_monitoring.sch
matbii/example/only-tracking/experiment.json
matbii/example/only-tracking/tracking.json
matbii/example/only-tracking/tracking.sch
matbii/extras/__init__.py
matbii/extras/scripts.py
matbii/extras/analysis/__init__.py
matbii/extras/analysis/get_guidance.py
matbii/extras/analysis/get_task.py
matbii/guidance/__init__.py
matbii/guidance/agent_base.py
matbii/guidance/agent_default.py
matbii/guidance/sensor_guidance.py
matbii/guidance/sensor_resource_management.py
matbii/guidance/sensor_system_monitoring.py
matbii/guidance/sensor_tracking.py
matbii/tasks/__init__.py
matbii/tasks/resource_management/__init__.py
matbii/tasks/resource_management/resource_management.py
matbii/tasks/resource_management/resource_management.sch
matbii/tasks/resource_management/resource_management.schema.json
matbii/tasks/resource_management/resource_management.svg.jinja
matbii/tasks/system_monitoring/__init__.py
matbii/tasks/system_monitoring/system_monitoring.py
matbii-0.0.11.dist-info/LICENSE
matbii-0.0.11.dist-info/METADATA
matbii-0.0.11.dist-info/WHEEL
matbii-0.0.11.dist-info/top_level.txt
matbii-0.0.11.dist-info/RECORD
