Metadata-Version: 2.1
Name: matbii
Version: 0.0.11
Summary: A configurable implementation of the MATB-II: Multi-Attribute Task Battery.
Author-email: Benedict Wilkins <benrjw@gmail.com>
License:                     GNU GENERAL PUBLIC LICENSE
Project-URL: Repository, https://github.com/dicelab-rhul/matbii
Requires-Python: >=3.10
License-File: LICENSE
Requires-Dist: icua[tobii]>=2.0.11
Requires-Dist: matplotlib
Requires-Dist: pandas
Requires-Dist: numpy
Provides-Extra: dev
Requires-Dist: pytest>=6.2.4; extra == "dev"
Requires-Dist: mkdocs; extra == "dev"
Requires-Dist: mkdocstrings; extra == "dev"
Requires-Dist: mkdocs-autorefs; extra == "dev"
Requires-Dist: mkdocs-gen-files; extra == "dev"
Requires-Dist: mkdocs-literate-nav; extra == "dev"
Requires-Dist: mkdocs-section-index; extra == "dev"
Requires-Dist: mkdocs-macros-plugin; extra == "dev"
Requires-Dist: mike; extra == "dev"
